MANIFEST.in
README.rst
setup.py
tests/__init__.py
tests/test_api.py
tests/test_config.py
tests/test_core.py
tests/test_meta.py
tests/test_models.py
tests/test_session.py
tests/test_ui.py
tests/test_utils.py
tests/tests.py
turses/__init__.py
turses/cli.py
turses/config.py
turses/core.py
turses/meta.py
turses/models.py
turses/session.py
turses/ui.py
turses/utils.py
turses.egg-info/PKG-INFO
turses.egg-info/SOURCES.txt
turses.egg-info/dependency_links.txt
turses.egg-info/entry_points.txt
turses.egg-info/pbr.json
turses.egg-info/requires.txt
turses.egg-info/top_level.txt
turses/api/__init__.py
turses/api/backends.py
turses/api/base.py
turses/api/debug.py
turses/api/helpers.py