Metadata-Version: 1.1
Name: turses
Version: 0.3.1
Summary: A Twitter client for the console.
Home-page: http://github.com/alejandrogomez/turses
Author: Alejandro Gómez
Author-email: alejandro@dialelo.com
License: UNKNOWN
Keywords: twitter client,curses,console,twitter
Platform: UNKNOWN
Classifier: Development Status :: 4 - Beta
Classifier: Environment :: Console :: Curses
Classifier: Intended Audience :: End Users/Desktop
Classifier: License :: OSI Approved :: GNU General Public License v3 (GPLv3)
Classifier: Natural Language :: English
Classifier: Operating System :: POSIX :: Linux
Classifier: Operating System :: MacOS
Classifier: Programming Language :: Python :: 2.6
Classifier: Programming Language :: Python :: 2.7
Classifier: Programming Language :: Python :: 3.3
Classifier: Programming Language :: Python :: 3.4
Classifier: Programming Language :: Python :: 3.5
Classifier: Topic :: Communications
